cemids/__init__.py
cemids/_version.py
cemids/helpers.py
cemids/log.py
cemids/Dtwrhs/Dtwrhs.py
cemids/Dtwrhs/__init__.py
cemids/Dtwrhs/reference.py
cemids/Ine/Ine.py
cemids/Ine/__init__.py
cemids/Ine/reference.py
cemids-0.0.2.dist-info/LICENSE
cemids-0.0.2.dist-info/METADATA
cemids-0.0.2.dist-info/WHEEL
cemids-0.0.2.dist-info/top_level.txt
cemids-0.0.2.dist-info/RECORD
